wcfhttp/__init__.py
wcfhttp/core.py
wcfhttp/main.py
wcfhttp-39.0.10.0.dist-info/METADATA
wcfhttp-39.0.10.0.dist-info/WHEEL
wcfhttp-39.0.10.0.dist-info/entry_points.txt
wcfhttp-39.0.10.0.dist-info/top_level.txt
wcfhttp-39.0.10.0.dist-info/RECORD
