Metadata-Version: 2.1
Name: wcfhttp
Version: 39.0.10.0
Summary: 一个玩微信的工具
Home-page: https://github.com/lich0821/WeChatFerry
Author: Changhua
Author-email: lichanghua0821@gmail.com
License: MIT
Project-URL: Documentation, https://wechatferry.readthedocs.io/zh/latest/index.html
Project-URL: GitHub, https://github.com/lich0821/WeChatFerry/
Classifier: Environment :: Win32 (MS Windows)
Classifier: Intended Audience :: Developers
Classifier: Intended Audience :: Customer Service
Classifier: Topic :: Communications :: Chat
Classifier: Operating System :: Microsoft :: Windows
Classifier: Programming Language :: Python
Requires-Python: >=3.8
Requires-Dist: setuptools
Requires-Dist: fastapi
Requires-Dist: uvicorn[standard]
Requires-Dist: wcferry (>=39.0.10.0)
